airbyte_agent_facebook_marketing/__init__.py
airbyte_agent_facebook_marketing/connector.py
airbyte_agent_facebook_marketing/connector_model.py
airbyte_agent_facebook_marketing/models.py
airbyte_agent_facebook_marketing/types.py
airbyte_agent_facebook_marketing/_vendored/__init__.py
airbyte_agent_facebook_marketing/_vendored/connector_sdk/__init__.py
airbyte_agent_facebook_marketing/_vendored/connector_sdk/auth_strategies.py
airbyte_agent_facebook_marketing/_vendored/connector_sdk/auth_template.py
airbyte_agent_facebook_marketing/_vendored/connector_sdk/connector_model_loader.py
airbyte_agent_facebook_marketing/_vendored/connector_sdk/constants.py
airbyte_agent_facebook_marketing/_vendored/connector_sdk/exceptions.py
airbyte_agent_facebook_marketing/_vendored/connector_sdk/extensions.py
airbyte_agent_facebook_marketing/_vendored/connector_sdk/http_client.py
airbyte_agent_facebook_marketing/_vendored/connector_sdk/introspection.py
airbyte_agent_facebook_marketing/_vendored/connector_sdk/secrets.py
airbyte_agent_facebook_marketing/_vendored/connector_sdk/types.py
airbyte_agent_facebook_marketing/_vendored/connector_sdk/utils.py
airbyte_agent_facebook_marketing/_vendored/connector_sdk/validation.py
airbyte_agent_facebook_marketing/_vendored/connector_sdk/validation_replication.py
airbyte_agent_facebook_marketing/_vendored/connector_sdk/cloud_utils/__init__.py
airbyte_agent_facebook_marketing/_vendored/connector_sdk/cloud_utils/client.py
airbyte_agent_facebook_marketing/_vendored/connector_sdk/executor/__init__.py
airbyte_agent_facebook_marketing/_vendored/connector_sdk/executor/hosted_executor.py
airbyte_agent_facebook_marketing/_vendored/connector_sdk/executor/local_executor.py
airbyte_agent_facebook_marketing/_vendored/connector_sdk/executor/models.py
airbyte_agent_facebook_marketing/_vendored/connector_sdk/http/__init__.py
airbyte_agent_facebook_marketing/_vendored/connector_sdk/http/config.py
airbyte_agent_facebook_marketing-0.1.5.dist-info/METADATA
airbyte_agent_facebook_marketing-0.1.5.dist-info/WHEEL
airbyte_agent_facebook_marketing-0.1.5.dist-info/RECORD
